abc_tool/__init__.py
abc_tool/main.py
abc_tool-0.1.0.dist-info/METADATA
abc_tool-0.1.0.dist-info/WHEEL
abc_tool-0.1.0.dist-info/RECORD
